gempaterkini/__init__.py
gempaterkini/main.py
latestearthquake_indonesia_mishbah-0.10.dist-info/LICENSE
latestearthquake_indonesia_mishbah-0.10.dist-info/METADATA
latestearthquake_indonesia_mishbah-0.10.dist-info/WHEEL
latestearthquake_indonesia_mishbah-0.10.dist-info/top_level.txt
latestearthquake_indonesia_mishbah-0.10.dist-info/RECORD
