Metadata-Version: 2.1
Name: latestearthquake-indonesia-mishbah
Version: 0.10
Summary: This package will get the latest earthquake from BMKG | Meteorological, Climatological, and Geophysical Agency
Home-page: https://github.com/dLiverdworks/latest-indonesia-earthquake
Author: Mishbahussuduri
Author-email: mishbahussuduri@gmail.com
Project-URL: Website, https://www.linkedin.com/in/mishbahussuduri/
Classifier: Programming Language :: Python :: 3
Classifier: License :: OSI Approved :: GNU General Public License v3 (GPLv3)
Classifier: Operating System :: OS Independent
Classifier: Development Status :: 5 - Production/Stable
Requires-Python: >=3.6
License-File: LICENSE
